scraid/__init__.py
scraid/advanced_request.py
tests/__init__.py
tests/test_advanced_request.py
scraid-0.12.dist-info/METADATA
scraid-0.12.dist-info/WHEEL
scraid-0.12.dist-info/top_level.txt
scraid-0.12.dist-info/RECORD
