Metadata-Version: 2.1
Name: scraid
Version: 0.12
Summary: A package for advanced Scrapy functionality and utilities.
Home-page: https://github.com/na0495/scraid
Author: na0495
Author-email: saad.mrabet@example.com
License: UNKNOWN
Platform: UNKNOWN
Classifier: Development Status :: 3 - Alpha
Classifier: License :: OSI Approved :: MIT License
Classifier: Programming Language :: Python :: 3
Classifier: Programming Language :: Python :: 3.6
Classifier: Programming Language :: Python :: 3.7
Classifier: Programming Language :: Python :: 3.8
Classifier: Programming Language :: Python :: 3.9
Classifier: Programming Language :: Python :: 3.10
Requires-Dist: fake-useragent
Requires-Dist: scrapy
